logwire/__init__.py
logwire/handler.py
logwire/client/__init__.py
logwire/client/apps.py
logwire/client/logs.py
logwire/client/workspaces.py
logwire-0.1.0.dev1.dist-info/METADATA
logwire-0.1.0.dev1.dist-info/WHEEL
logwire-0.1.0.dev1.dist-info/top_level.txt
logwire-0.1.0.dev1.dist-info/RECORD
